.gitignore
.travis.yml
MANIFEST.in
README.mdown
setup.py
django_icybackup.egg-info/PKG-INFO
django_icybackup.egg-info/SOURCES.txt
django_icybackup.egg-info/dependency_links.txt
django_icybackup.egg-info/requires.txt
django_icybackup.egg-info/top_level.txt
icybackup/__init__.py
icybackup/admin.py
icybackup/models.py
icybackup/components/__init__.py
icybackup/components/db.py
icybackup/components/glacier.py
icybackup/components/lib.py
icybackup/management/__init__.py
icybackup/management/commands/__init__.py
icybackup/management/commands/backup.py
icybackup/management/commands/restore.py
icybackup/migrations/0001_initial.py
icybackup/migrations/0002_auto__add_glacierinventory.py
icybackup/migrations/0003_auto__add_field_glacierinventory_requested_date.py
icybackup/migrations/0004_auto__chg_field_glacierbackup_date.py
icybackup/migrations/__init__.py