Metadata-Version: 1.0
Name: django-icybackup
Version: 0.1.1
Summary: A Django database/media backup tool with Amazon Glacier and local folder support
Home-page: https://github.com/stbarnabas/django-icybackup
Author: Adam Brenecki, St Barnabas' Theological College
Author-email: abrenecki@sbtc.org.au
License: UNKNOWN
Platform: UNKNOWN
